test/__init__.py
test/setup.py
recommendation8-0.1.dist-info/LICENSE.txt
recommendation8-0.1.dist-info/METADATA
recommendation8-0.1.dist-info/WHEEL
recommendation8-0.1.dist-info/top_level.txt
recommendation8-0.1.dist-info/RECORD
