Metadata-Version: 2.1
Name: recommendation8
Version: 0.1
Summary: Food Recommendation system
Author: Lohitha
Author-email: lohitha.m003@gmail.com
License-File: LICENSE.txt
